code2parquet_local.py
code2parquet_local_python.py
code2parquet_s3_python.py
code2parquet_transform.py
code2parquet_transform_python.py
dpk_code2parquet_transform_python-0.2.0.dist-info/METADATA
dpk_code2parquet_transform_python-0.2.0.dist-info/WHEEL
dpk_code2parquet_transform_python-0.2.0.dist-info/top_level.txt
dpk_code2parquet_transform_python-0.2.0.dist-info/RECORD
