Metadata-Version: 2.1
Name: dpk_code2parquet_transform_python
Version: 0.2.0
Summary: code2parquet Python Transform
Author-email: David Wood <dawood@us.ibm.com>, Boris Lublinsky <blublinsky@ibm.com>
License: Apache-2.0
Requires-Python: >=3.10
Requires-Dist: data-prep-toolkit ==0.2.0
Requires-Dist: parameterized
Requires-Dist: pandas
Provides-Extra: dev
Requires-Dist: twine ; extra == 'dev'
Requires-Dist: pytest >=7.3.2 ; extra == 'dev'
Requires-Dist: pytest-dotenv >=0.5.2 ; extra == 'dev'
Requires-Dist: pytest-env >=1.0.0 ; extra == 'dev'
Requires-Dist: pre-commit >=3.3.2 ; extra == 'dev'
Requires-Dist: pytest-cov >=4.1.0 ; extra == 'dev'
Requires-Dist: pytest-mock >=3.10.0 ; extra == 'dev'
Requires-Dist: moto ==5.0.5 ; extra == 'dev'
Requires-Dist: markupsafe ==2.0.1 ; extra == 'dev'
